{
  "main": {
    "id": "03956de37bd9e2cb",
    "type": "split",
    "children": [
      {
        "id": "d4d9c43aa74b8d05",
        "type": "tabs",
        "children": [
          {
            "id": "3a04fee322124b00",
            "type": "leaf",
            "state": {
              "type": "markdown",
              "state": {
                "file": "NSU/LaSalle teorema.md",
                "mode": "source",
                "source": false
              }
            }
          },
          {
            "id": "11f6a1e11f4def18",
            "type": "leaf",
            "state": {
              "type": "markdown",
              "state": {
                "file": "NS2/Untitled.md",
                "mode": "source",
                "source": false
              }
            }
          }
        ],
        "currentTab": 1
      }
    ],
    "direction": "vertical"
  },
  "left": {
    "id": "d88ffee2f0eb8640",
    "type": "split",
    "children": [
      {
        "id": "e597a7b38e0d8ec5",
        "type": "tabs",
        "children": [
          {
            "id": "be6771d687a6266a",
            "type": "leaf",
            "state": {
              "type": "file-explorer",
              "state": {
                "sortOrder": "alphabetical"
              }
            }
          },
          {
            "id": "dba37509b1851e74",
            "type": "leaf",
            "state": {
              "type": "search",
              "state": {
                "query": "",
                "matchingCase": false,
                "explainSearch": false,
                "collapseAll": false,
                "extraContext": false,
                "sortOrder": "alphabetical"
              }
            }
          },
          {
            "id": "cfd0b63363c372fa",
            "type": "leaf",
            "state": {
              "type": "bookmarks",
              "state": {}
            }
          }
        ]
      }
    ],
    "direction": "horizontal",
    "width": 300
  },
  "right": {
    "id": "39de089dde03670f",
    "type": "split",
    "children": [
      {
        "id": "032bddfd4ae3d1e5",
        "type": "tabs",
        "children": [
          {
            "id": "61db6953f7ef50d6",
            "type": "leaf",
            "state": {
              "type": "backlink",
              "state": {
                "file": "NSU/LaSalle teorema.md",
                "collapseAll": false,
                "extraContext": false,
                "sortOrder": "alphabetical",
                "showSearch": false,
                "searchQuery": "",
                "backlinkCollapsed": false,
                "unlinkedCollapsed": true
              }
            }
          },
          {
            "id": "59913e5631d52406",
            "type": "leaf",
            "state": {
              "type": "outgoing-link",
              "state": {
                "file": "NSU/LaSalle teorema.md",
                "linksCollapsed": false,
                "unlinkedCollapsed": true
              }
            }
          },
          {
            "id": "110122b1fb33d990",
            "type": "leaf",
            "state": {
              "type": "tag",
              "state": {
                "sortOrder": "frequency",
                "useHierarchy": true
              }
            }
          },
          {
            "id": "43811f3b72ffd499",
            "type": "leaf",
            "state": {
              "type": "outline",
              "state": {
                "file": "NSU/LaSalle teorema.md"
              }
            }
          }
        ]
      }
    ],
    "direction": "horizontal",
    "width": 300,
    "collapsed": true
  },
  "left-ribbon": {
    "hiddenItems": {
      "switcher:Open quick switcher": false,
      "graph:Open graph view": false,
      "canvas:Create new canvas": false,
      "daily-notes:Open today's daily note": false,
      "templates:Insert template": false,
      "command-palette:Open command palette": false
    }
  },
  "active": "be6771d687a6266a",
  "lastOpenFiles": [
    "NSU/LaSalle teorema.md",
    "NS2/Untitled.md",
    "URV",
    "NS2",
    "DOS/Diskretna Furijeova Transformacija.md",
    "SIS/Furijeova transformacija.md",
    "Diskretna Furijeova Transformacija.md",
    "SIS/z-transformacija.md",
    "SIS",
    "Laplasova transformacija.md",
    "Laplasova.md",
    "DOS/Poduzorkovanje.md",
    "ETF",
    "DOS/Teorema o odabiranju.md",
    "DOS/Rotacioni faktor.md",
    "SAU2/Funkcija povratnog prenosa.md",
    "SAU2/Funkcija osetljivosti.md",
    "SAU2/Klag.md",
    "NSU/2010Sept, II deo ispita.md",
    "DOS",
    "NSU/Egzistencija samooscilacija.md",
    "NSU/Invarijantni skupovi.md",
    "NSU/Ljapunov stabilnost.md",
    "NSU/Bendixonov kriterijum.md",
    "SAU2/Routh-Hurwitz kriterijum.md",
    "NSU/Relejni eksperiment.md",
    "SAU2/Bodeovi parametri.md",
    "SAU2/Klead.md",
    "Bodeovi parametri(Bodeove karakteristike).md",
    "Images/gs1.jpg",
    "NSU/Opisna funkcija nelinearnosti.md",
    "NSU/Harmonijska linearizacija.md",
    "SAU2",
    "Images/Pasted image 20230808004653.png",
    "Images/Pasted image 20230808004031.png",
    "Images/FrequencyResponseTutorial_BodePlots_Margins_MarginDiagrams.png",
    "Images",
    "Images/IMG_E0110.JPG",
    "Images/IMG_E0108.JPG",
    "NSU",
    "Polje(matematika)"
  ]
}